LICENSE
MANIFEST.in
README.md
setup.py
flask_handlers/__init__.py
flask_handlers/json_error.py
flask_handlers.egg-info/PKG-INFO
flask_handlers.egg-info/SOURCES.txt
flask_handlers.egg-info/dependency_links.txt
flask_handlers.egg-info/not-zip-safe
flask_handlers.egg-info/top_level.txt