Metadata-Version: 1.1
Name: flask-handlers
Version: 0.0.1
Summary: Handlers for Flask applications
Home-page: https://github.com/lucascarvalho/flask-handlers
Author: Lucas Carvalho
Author-email: lucascarvalho@gmail.com
License: MIT License
